presidio_vault/__init__.py
presidio_vault/vault.py
presidio_vault-0.1.0.dist-info/METADATA
presidio_vault-0.1.0.dist-info/WHEEL
presidio_vault-0.1.0.dist-info/RECORD
