Metadata-Version: 2.1
Name: presidio-vault
Version: 0.1.0
Summary: A HashiCorp Vault operator that allows anonymization and de-anonymization using Microsoft Presidio.
License: MIT
Author: Akshay Karle
Author-email: 1443108+akshaykarle@users.noreply.github.com
Requires-Python: >=3.8,<4.0
Classifier: License :: OSI Approved :: MIT License
Classifier: Programming Language :: Python :: 3
Classifier: Programming Language :: Python :: 3.8
Classifier: Programming Language :: Python :: 3.9
Classifier: Programming Language :: Python :: 3.10
Classifier: Programming Language :: Python :: 3.11
Classifier: Programming Language :: Python :: 3.12
Requires-Dist: hvac (>=2.3.0,<3.0.0)
Requires-Dist: presidio-anonymizer (>=2.2.355,<3.0.0)
